py2asm/__init__.py
py2asm/setup.py
py2asm-0.3.dist-info/METADATA
py2asm-0.3.dist-info/WHEEL
py2asm-0.3.dist-info/top_level.txt
py2asm-0.3.dist-info/RECORD
