Metadata-Version: 2.1
Name: py2asm
Version: 0.3
Summary: A package for converting python to asm compiled code
Home-page: https://github.com/SCORPIA-oss/python-to-asm
Author: py2asm group
Author-email: xsumagravity@gmail.com
License: UNKNOWN
Platform: UNKNOWN
Classifier: Programming Language :: Python :: 3
Classifier: License :: OSI Approved :: MIT License
Classifier: Operating System :: MacOS
Requires-Python: >=3.6
